ai_trainer_bot/__init__.py
ai_trainer_bot/cli/__init__.py
ai_trainer_bot/cli/main.py
ai_trainer_bot/config/__init__.py
ai_trainer_bot/config/eval.yml
ai_trainer_bot/config/train.yml
ai_trainer_bot/core/__init__.py
ai_trainer_bot/core/config.py
ai_trainer_bot/core/state.py
ai_trainer_bot/core/trainer.py
ai_trainer_bot/data/__init__.py
ai_trainer_bot/data/augmentor.py
ai_trainer_bot/data/loader.py
ai_trainer_bot/data/preprocessor.py
ai_trainer_bot/data/transforms.py
ai_trainer_bot/metrics/__init__.py
ai_trainer_bot/metrics/classification.py
ai_trainer_bot/metrics/custom.py
ai_trainer_bot/metrics/regression.py
ai_trainer_bot/models/__init__.py
ai_trainer_bot/models/base.py
ai_trainer_bot/models/registry.py
ai_trainer_bot/models/architectures/__init__.py
ai_trainer_bot/models/architectures/cnn.py
ai_trainer_bot/models/architectures/rnn.py
ai_trainer_bot/models/architectures/transformer.py
ai_trainer_bot/serving/__init__.py
ai_trainer_bot/serving/exporter.py
ai_trainer_bot/serving/inference.py
ai_trainer_bot/serving/onnx_export.py
ai_trainer_bot/serving/torchscript_export.py
ai_trainer_bot/tracking/__init__.py
ai_trainer_bot/tracking/artifact_store.py
ai_trainer_bot/tracking/experiment_tracker.py
ai_trainer_bot/tracking/logger.py
ai_trainer_bot/training/__init__.py
ai_trainer_bot/training/callbacks.py
ai_trainer_bot/training/losses.py
ai_trainer_bot/training/optimizers.py
ai_trainer_bot/training/schedulers.py
ai_trainer_bot/tuning/__init__.py
ai_trainer_bot/tuning/bayesian_search.py
ai_trainer_bot/tuning/grid_search.py
ai_trainer_bot/tuning/random_search.py
ai_trainer_bot/utils/__init__.py
ai_trainer_bot/utils/helpers.py
tests/__init__.py
ai_trainer_bot-0.0.1.dist-info/METADATA
ai_trainer_bot-0.0.1.dist-info/WHEEL
ai_trainer_bot-0.0.1.dist-info/entry_points.txt
ai_trainer_bot-0.0.1.dist-info/top_level.txt
ai_trainer_bot-0.0.1.dist-info/RECORD
