Metadata-Version: 2.4
Name: ai-trainer-bot
Version: 0.0.1
Summary: A comprehensive machine learning training framework
Home-page: https://github.com/girish-kor/ai-trainer-bot
Author: Girish Kor
Author-email: girishkor05@gmail.com
License: MIT
Project-URL: Bug Reports, https://github.com/girish-kor/ai-trainer-bot/issues
Project-URL: Source, https://github.com/girish-kor/ai-trainer-bot
Project-URL: Documentation, https://ai-trainer-bot.readthedocs.io/
Keywords: machine learning,deep learning,pytorch,training,framework
Classifier: Development Status :: 3 - Alpha
Classifier: Intended Audience :: Developers
Classifier: Intended Audience :: Science/Research
Classifier: Operating System :: OS Independent
Classifier: Programming Language :: Python :: 3
Classifier: Programming Language :: Python :: 3.8
Classifier: Programming Language :: Python :: 3.9
Classifier: Programming Language :: Python :: 3.10
Classifier: Programming Language :: Python :: 3.11
Classifier: Topic :: Scientific/Engineering :: Artificial Intelligence
Classifier: Topic :: Software Development :: Libraries :: Python Modules
Requires-Python: >=3.8
Provides-Extra: dev
Requires-Dist: black>=21.0.0; extra == "dev"
Requires-Dist: flake8>=4.0.0; extra == "dev"
Requires-Dist: mypy>=0.910; extra == "dev"
Requires-Dist: pre-commit>=2.15.0; extra == "dev"
Requires-Dist: pytest>=6.2.0; extra == "dev"
Requires-Dist: pytest-cov>=2.12.0; extra == "dev"
Provides-Extra: docs
Requires-Dist: sphinx>=4.2.0; extra == "docs"
Requires-Dist: sphinx-rtd-theme>=1.0.0; extra == "docs"
Provides-Extra: gpu
Requires-Dist: torch>=1.9.0; extra == "gpu"
Requires-Dist: torchvision>=0.10.0; extra == "gpu"
Requires-Dist: torchaudio>=0.9.0; extra == "gpu"
Dynamic: author
Dynamic: author-email
Dynamic: classifier
Dynamic: description
Dynamic: description-content-type
Dynamic: home-page
Dynamic: keywords
Dynamic: license
Dynamic: project-url
Dynamic: provides-extra
Dynamic: requires-python
Dynamic: summary
